{"trial_id": "9c0c032ec527f8a39d05443d55b0c62a", "hyperparameters": {"space": [{"class_name": "Int", "config": {"name": "num_of_neurons0", "default": null, "conditions": [], "min_value": 10, "max_value": 50, "step": 5, "sampling": null}}, {"class_name": "Int", "config": {"name": "num_of_neurons1", "default": null, "conditions": [], "min_value": 10, "max_value": 50, "step": 5, "sampling": null}}, {"class_name": "Int", "config": {"name": "num_of_neurons2", "default": null, "conditions": [], "min_value": 10, "max_value": 50, "step": 5, "sampling": null}}, {"class_name": "Int", "config": {"name": "num_of_neurons3", "default": null, "conditions": [], "min_value": 10, "max_value": 50, "step": 5, "sampling": null}}, {"class_name": "Choice", "config": {"name": "learning_rate", "default": 0.09, "conditions": [], "values": [0.09, 0.095, 0.001, 0.0015], "ordered": true}}], "values": {"num_of_neurons0": 45, "num_of_neurons1": 15, "num_of_neurons2": 10, "num_of_neurons3": 30, "learning_rate": 0.095, "tuner/epochs": 2, "tuner/initial_epoch": 0, "tuner/bracket": 3, "tuner/round": 0}}, "metrics": {"metrics": {"loss": {"direction": "min", "observations": [{"value": [3.25740385055542], "step": 0}]}, "accuracy": {"direction": "max", "observations": [{"value": [0.6323000192642212], "step": 0}]}, "val_loss": {"direction": "min", "observations": [{"value": [0.7244969606399536], "step": 0}]}, "val_accuracy": {"direction": "max", "observations": [{"value": [0.6554800271987915], "step": 0}]}}}, "score": 0.6554800271987915, "best_step": 0, "status": "COMPLETED"}